classifier_model/VERSION
classifier_model/__init__.py
classifier_model/config.yml
classifier_model/pipeline.py
classifier_model/predict.py
classifier_model/train_pipeline.py
classifier_model/config/__init__.py
classifier_model/config/core.py
classifier_model/datasets/__init__.py
classifier_model/datasets/raw.csv
classifier_model/datasets/test.csv
classifier_model/datasets/train.csv
classifier_model/processing/__init__.py
classifier_model/processing/data_manager.py
classifier_model/processing/features.py
classifier_model/processing/validation.py
classifier_model/trained_models/__init__.py
classifier_model/trained_models/classifier_model_output_v0.0.9.pkl
tid_classifier_model-0.0.9.dist-info/METADATA
tid_classifier_model-0.0.9.dist-info/WHEEL
tid_classifier_model-0.0.9.dist-info/top_level.txt
tid_classifier_model-0.0.9.dist-info/RECORD
